natal/__init__.py
natal/ai.py
natal/chart.py
natal/classes.py
natal/config.py
natal/const.py
natal/data.py
natal/seas_18.se1
natal/stats.py
natal/utils.py
natal/svg_paths/air.svg
natal/svg_paths/aquarius.svg
natal/svg_paths/aries.svg
natal/svg_paths/asc.svg
natal/svg_paths/cancer.svg
natal/svg_paths/capricorn.svg
natal/svg_paths/cardinal.svg
natal/svg_paths/ceres.svg
natal/svg_paths/chiron.svg
natal/svg_paths/clean_up.py
natal/svg_paths/conjunction.svg
natal/svg_paths/detriment.svg
natal/svg_paths/domicile.svg
natal/svg_paths/dsc.svg
natal/svg_paths/earth.svg
natal/svg_paths/exaltation.svg
natal/svg_paths/fall.svg
natal/svg_paths/fire.svg
natal/svg_paths/fixed.svg
natal/svg_paths/gemini.svg
natal/svg_paths/ic.svg
natal/svg_paths/juno.svg
natal/svg_paths/jupiter.svg
natal/svg_paths/leo.svg
natal/svg_paths/libra.svg
natal/svg_paths/mars.svg
natal/svg_paths/mc.svg
natal/svg_paths/mercury.svg
natal/svg_paths/moon.svg
natal/svg_paths/mutable.svg
natal/svg_paths/neptune.svg
natal/svg_paths/north_node.svg
natal/svg_paths/opposition.svg
natal/svg_paths/pallas.svg
natal/svg_paths/pisces.svg
natal/svg_paths/pluto.svg
natal/svg_paths/quincunx.svg
natal/svg_paths/retrograde.svg
natal/svg_paths/sagittarius.svg
natal/svg_paths/saturn.svg
natal/svg_paths/scorpio.svg
natal/svg_paths/sextile.svg
natal/svg_paths/south_node.svg
natal/svg_paths/square.svg
natal/svg_paths/sun.svg
natal/svg_paths/taurus.svg
natal/svg_paths/trine.svg
natal/svg_paths/uranus.svg
natal/svg_paths/venus.svg
natal/svg_paths/vesta.svg
natal/svg_paths/virgo.svg
natal/svg_paths/water.svg
natal-1.0.7.dist-info/METADATA
natal-1.0.7.dist-info/WHEEL
natal-1.0.7.dist-info/licenses/LICENSE
natal-1.0.7.dist-info/RECORD
