Metadata-Version: 2.4
Name: natal
Version: 1.0.7
Summary: create Natal Chart with ease
Project-URL: Repository, https://github.com/hoishing/natal
Author-email: Kelvin Ng <hoishing@gmail.com>
License: MIT
License-File: LICENSE
Requires-Python: >=3.12
Requires-Dist: pydantic>=2.8.2
Requires-Dist: pyswisseph>=2.10.3.2
Requires-Dist: tagit>=0.6.1
